{"wholeCity": [{"date": "2026-07-01", "price": "13.40"}, {"date": "2026-07-02", "price": "13.41"}, {"date": "2026-07-03", "price": "13.41"}, {"date": "2026-07-04", "price": "13.41"}], "urbanCity": [{"date": "2026-07-01", "price": "13.93"}, {"date": "2026-07-02", "price": "13.93"}, {"date": "2026-07-03", "price": "13.93"}, {"date": "2026-07-04", "price": "13.93"}], "suburbCity": [{"date": "2026-07-01", "price": "12.24"}, {"date": "2026-07-02", "price": "12.28"}, {"date": "2026-07-03", "price": "12.28"}, {"date": "2026-07-04", "price": "12.28"}]}