{"wholeCity": [{"date": "2025-10-01", "price": "6.06"}, {"date": "2025-10-02", "price": "6.00"}, {"date": "2025-10-03", "price": "6.00"}, {"date": "2025-10-04", "price": "6.00"}, {"date": "2025-10-05", "price": "6.00"}, {"date": "2025-10-06", "price": "6.00"}], "urbanCity": [{"date": "2025-10-01", "price": "6.11"}, {"date": "2025-10-02", "price": "6.11"}, {"date": "2025-10-03", "price": "6.11"}, {"date": "2025-10-04", "price": "6.11"}, {"date": "2025-10-05", "price": "6.11"}, {"date": "2025-10-06", "price": "6.11"}], "suburbCity": [{"date": "2025-10-01", "price": "6.50"}, {"date": "2025-10-02", "price": "6.38"}, {"date": "2025-10-03", "price": "6.38"}, {"date": "2025-10-04", "price": "6.38"}, {"date": "2025-10-05", "price": "6.38"}, {"date": "2025-10-06", "price": "6.38"}]}