{"wholeCity": [{"date": "2026-04-01", "price": "9.81"}, {"date": "2026-04-02", "price": "9.88"}, {"date": "2026-04-03", "price": "9.94"}, {"date": "2026-04-04", "price": "9.94"}], "urbanCity": [{"date": "2026-04-01", "price": "10.00"}, {"date": "2026-04-02", "price": "10.00"}, {"date": "2026-04-03", "price": "10.11"}, {"date": "2026-04-04", "price": "10.11"}], "suburbCity": [{"date": "2026-04-01", "price": "10.38"}, {"date": "2026-04-02", "price": "10.38"}, {"date": "2026-04-03", "price": "10.38"}, {"date": "2026-04-04", "price": "10.38"}]}