{"本地菜心": {"wholeCity": "10.03", "urbanCity": "11.19", "suburbCity": "9.13"}, "矮脚白菜": {"wholeCity": "10.44", "urbanCity": "11.22", "suburbCity": "10.25"}, "本地白菜": {"wholeCity": "7.44", "urbanCity": "8.22", "suburbCity": "6.88"}, "小塘白菜": {"wholeCity": "7.51", "urbanCity": "7.96", "suburbCity": "7.20"}, "大芥菜": {"wholeCity": "7.52", "urbanCity": "7.97", "suburbCity": "8.00"}, "生菜": {"wholeCity": "8.94", "urbanCity": "8.89", "suburbCity": "9.50"}, "西生菜": {"wholeCity": "11.06", "urbanCity": "11.33", "suburbCity": "10.86"}, "菠菜": {"wholeCity": "12.66", "urbanCity": "13.00", "suburbCity": "12.69"}, "油麦菜": {"wholeCity": "8.18", "urbanCity": "8.31", "suburbCity": "8.13"}, "绍菜": {"wholeCity": "5.68", "urbanCity": "5.73", "suburbCity": "5.50"}, "西洋菜": {"wholeCity": "10.44", "urbanCity": "10.56", "suburbCity": "10.86"}, "西红柿": {"wholeCity": "8.94", "urbanCity": "9.00", "suburbCity": "9.25"}, "芥兰": {"wholeCity": "10.03", "urbanCity": "10.05", "suburbCity": "9.88"}, "红萝卜": {"wholeCity": "6.31", "urbanCity": "6.44", "suburbCity": "6.63"}, "白萝卜": {"wholeCity": "4.06", "urbanCity": "4.11", "suburbCity": "4.50"}, "椰菜花": {"wholeCity": "9.21", "urbanCity": "9.60", "suburbCity": "9.38"}, "西兰花": {"wholeCity": "10.06", "urbanCity": "9.89", "suburbCity": "10.75"}, "水空心菜": {"wholeCity": "7.73", "urbanCity": "8.16", "suburbCity": "7.79"}, "青皮冬瓜": {"wholeCity": "4.23", "urbanCity": "4.40", "suburbCity": "4.38"}, "青瓜": {"wholeCity": "7.76", "urbanCity": "7.58", "suburbCity": "8.38"}, "茄瓜": {"wholeCity": "7.31", "urbanCity": "7.16", "suburbCity": "7.56"}, "青豆角": {"wholeCity": "12.77", "urbanCity": "14.67", "suburbCity": "11.25"}, "白豆角": {"wholeCity": "10.27", "urbanCity": "10.78", "suburbCity": "10.29"}, "土豆": {"wholeCity": "6.14", "urbanCity": "6.24", "suburbCity": "6.38"}, "本地芹菜": {"wholeCity": "11.00", "urbanCity": "12.00", "suburbCity": "11.50"}, "西芹": {"wholeCity": "8.50", "urbanCity": "9.00", "suburbCity": "9.13"}, "莴笋": {"wholeCity": "7.59", "urbanCity": "7.16", "suburbCity": "8.50"}, "椰菜": {"wholeCity": "5.29", "urbanCity": "5.40", "suburbCity": "5.38"}, "大蒜": {"wholeCity": "12.44", "urbanCity": "14.11", "suburbCity": "11.75"}, "蒜心": {"wholeCity": "15.88", "urbanCity": "16.89", "suburbCity": "15.50"}, "云南小瓜": {"wholeCity": "8.39", "urbanCity": "8.91", "suburbCity": "9.00"}, "丝瓜": {"wholeCity": "9.88", "urbanCity": "10.33", "suburbCity": "9.75"}, "苦瓜": {"wholeCity": "7.77", "urbanCity": "8.04", "suburbCity": "8.00"}, "南瓜": {"wholeCity": "6.18", "urbanCity": "6.87", "suburbCity": "6.25"}, "圆椒": {"wholeCity": "11.88", "urbanCity": "12.00", "suburbCity": "12.00"}, "青尖椒": {"wholeCity": "9.19", "urbanCity": "9.78", "suburbCity": "9.38"}, "荷兰豆": {"wholeCity": "20.69", "urbanCity": "18.75", "suburbCity": "24.38"}, "小豆芽菜": {"wholeCity": "4.73", "urbanCity": "5.22", "suburbCity": "4.43"}, "韭菜": {"wholeCity": "9.73", "urbanCity": "9.73", "suburbCity": "9.75"}, "洋葱": {"wholeCity": "6.63", "urbanCity": "6.78", "suburbCity": "6.38"}, "大肉姜": {"wholeCity": "18.19", "urbanCity": "20.00", "suburbCity": "16.50"}, "莲藕": {"wholeCity": "11.59", "urbanCity": "11.49", "suburbCity": "11.88"}, "蒜头": {"wholeCity": "17.06", "urbanCity": "18.67", "suburbCity": "15.25"}, "冻排骨": {"wholeCity": "44.69", "urbanCity": "49.11", "suburbCity": "34.33"}, "冻鸡翼": {"wholeCity": "38.19", "urbanCity": "40.00", "suburbCity": "37.00"}, "冻凤爪": {"wholeCity": "41.27", "urbanCity": "41.50", "suburbCity": "38.14"}, "冻带鱼": {"wholeCity": "54.87", "urbanCity": "56.22", "suburbCity": "46.86"}, "冻黄花鱼": {"wholeCity": "57.75", "urbanCity": "57.56", "suburbCity": "55.50"}, "红三鱼": {"wholeCity": "72.80", "urbanCity": "72.00", "suburbCity": "73.57"}, "鱿鱼": {"wholeCity": "63.88", "urbanCity": "63.78", "suburbCity": "66.00"}, "生鱼": {"wholeCity": "29.20", "urbanCity": "31.78", "suburbCity": "27.00"}, "黄鳝": {"wholeCity": "62.36", "urbanCity": "65.67", "suburbCity": "57.43"}, "原条草鱼": {"wholeCity": "23.00", "urbanCity": "25.38", "suburbCity": "20.75"}, "开刀草鱼": {"wholeCity": "30.94", "urbanCity": "31.33", "suburbCity": "29.88"}, "原条鳙鱼": {"wholeCity": "22.93", "urbanCity": "21.17", "suburbCity": "22.75"}, "开刀鳙鱼": {"wholeCity": "22.43", "urbanCity": "21.43", "suburbCity": "22.57"}, "原条鲮鱼": {"wholeCity": "34.54", "urbanCity": "37.14", "suburbCity": "28.83"}, "鲫鱼": {"wholeCity": "28.30", "urbanCity": "28.86", "suburbCity": "27.31"}, "鲈鱼": {"wholeCity": "44.00", "urbanCity": "44.44", "suburbCity": "43.50"}, "精瘦肉": {"wholeCity": "37.63", "urbanCity": "38.44", "suburbCity": "39.50"}, "有皮上肉": {"wholeCity": "31.72", "urbanCity": "34.00", "suburbCity": "32.19"}, "肋条肉": {"wholeCity": "33.25", "urbanCity": "33.44", "suburbCity": "33.88"}, "排骨": {"wholeCity": "59.19", "urbanCity": "59.78", "suburbCity": "60.88"}, "鲜牛肉": {"wholeCity": "106.00", "urbanCity": "102.00", "suburbCity": "108.00"}, "生宰光鸡": {"wholeCity": "38.63", "urbanCity": "34.50", "suburbCity": "37.71"}, "红壳鸡蛋": {"wholeCity": "11.57", "urbanCity": "11.76", "suburbCity": "11.52"}, "黄豆": {"wholeCity": "10.25"}, "红豆": {"wholeCity": "16.94"}, "绿豆": {"wholeCity": "15.41"}, "花生米": {"wholeCity": "15.57"}, "玉米粉": {"wholeCity": "6.50"}, "粳米": {"wholeCity": "6.23"}, "早籼米": {"wholeCity": "5.95"}, "晚籼米": {"wholeCity": "6.50"}, "丝苗米": {"wholeCity": "7.26"}, "特一粉": {"wholeCity": "7.17"}, "标面粉": {"wholeCity": "5.57"}, "5L金龙鱼食用调和油": {"wholeCity": "66.57"}, "5L鲁花压榨一级花生油": {"wholeCity": "153.75"}, "5L胡姬花古法花生油": {"wholeCity": "150.33"}, "苹果": {"wholeCity": "14.24"}, "雪梨": {"wholeCity": "10.67"}, "香梨": {"wholeCity": "15.50"}, "潮州柑": {"wholeCity": "12.00"}, "香蕉": {"wholeCity": "6.60"}, "西瓜": {"wholeCity": "7.00"}, "柚子": {"wholeCity": "12.00"}, "哈密瓜": {"wholeCity": "11.00"}, "桃子": {"wholeCity": "30.00"}, "红提": {"wholeCity": "43.00"}, "橙子": {"wholeCity": "12.40"}, "伊利纯牛奶": {"wholeCity": "3.00"}, "蒙牛纯牛奶": {"wholeCity": "3.00"}}