{"wholeCity": [{"date": "2025-07-01", "price": "9.32"}, {"date": "2025-07-02", "price": "9.13"}, {"date": "2025-07-03", "price": "9.13"}, {"date": "2025-07-04", "price": "9.00"}, {"date": "2025-07-05", "price": "9.19"}, {"date": "2025-07-06", "price": "9.25"}, {"date": "2025-07-07", "price": "9.06"}, {"date": "2025-07-08", "price": "9.38"}, {"date": "2025-07-09", "price": "9.41"}, {"date": "2025-07-10", "price": "9.48"}, {"date": "2025-07-11", "price": "9.44"}, {"date": "2025-07-12", "price": "9.44"}, {"date": "2025-07-13", "price": "9.47"}, {"date": "2025-07-14", "price": "9.47"}], "urbanCity": [{"date": "2025-07-01", "price": "9.51"}, {"date": "2025-07-02", "price": "9.33"}, {"date": "2025-07-03", "price": "9.33"}, {"date": "2025-07-04", "price": "9.11"}, {"date": "2025-07-05", "price": "9.44"}, {"date": "2025-07-06", "price": "9.67"}, {"date": "2025-07-07", "price": "9.56"}, {"date": "2025-07-08", "price": "9.89"}, {"date": "2025-07-09", "price": "9.96"}, {"date": "2025-07-10", "price": "10.18"}, {"date": "2025-07-11", "price": "10.11"}, {"date": "2025-07-12", "price": "10.11"}, {"date": "2025-07-13", "price": "10.11"}, {"date": "2025-07-14", "price": "10.00"}], "suburbCity": [{"date": "2025-07-01", "price": "10.19"}, {"date": "2025-07-02", "price": "10.00"}, {"date": "2025-07-03", "price": "10.00"}, {"date": "2025-07-04", "price": "10.00"}, {"date": "2025-07-05", "price": "10.00"}, {"date": "2025-07-06", "price": "10.00"}, {"date": "2025-07-07", "price": "9.75"}, {"date": "2025-07-08", "price": "9.88"}, {"date": "2025-07-09", "price": "9.88"}, {"date": "2025-07-10", "price": "9.88"}, {"date": "2025-07-11", "price": "9.88"}, {"date": "2025-07-12", "price": "9.88"}, {"date": "2025-07-13", "price": "9.94"}, {"date": "2025-07-14", "price": "10.06"}]}